LICENSE
MANIFEST.in
README.md
cytime_test.pyx
setup.cfg
setup.py
./cytime_test.pyx
./cytime/__init__.pxd
./cytime/cytime.pxd
./cytime/cytime.pyx
cytime/__init__.py
cytime/timemodule.c
cytime.egg-info/PKG-INFO
cytime.egg-info/SOURCES.txt
cytime.egg-info/dependency_links.txt
cytime.egg-info/top_level.txt