Metadata-Version: 1.0
Name: cytime
Version: 0.1
Summary: Cdef wrappings of functions from Python's time module.
Home-page: https://github.com/robertwb/cytime
Author: Robert Bradshaw
Author-email: robertwb@gmail.com
License: Apache
Platform: UNKNOWN
